splunk_otel/__about__.py
splunk_otel/__init__.py
splunk_otel/configurator.py
splunk_otel/distro.py
splunk_otel/env.py
splunk_otel/profile.py
splunk_otel/profile_pb2.py
splunk_otel/propagator.py
splunk_opentelemetry-2.9.0.dist-info/METADATA
splunk_opentelemetry-2.9.0.dist-info/WHEEL
splunk_opentelemetry-2.9.0.dist-info/entry_points.txt
splunk_opentelemetry-2.9.0.dist-info/licenses/LICENSE.txt
splunk_opentelemetry-2.9.0.dist-info/RECORD
